{
    "$id": "hub.jupyter.org/server-action",
    "version": 1,
    "title": "JupyterHub server events",
    "description": "JupyterHub emits this event when a user's server starts or stops",
    "type": "object",
    "properties": {
        "action": {
            "enum": [
                "start",
                "stop"
            ],
            "description": "Action taken on this user's server"
        },
        "username": {
            "type": "string",
            "description": "Name of the user whose server this action applies to"
        },
        "servername": {
            "type": "string",
            "description": "Name of the server this action applies to"
        }
    }
}